setup.py
anovelmous_grammar.egg-info/PKG-INFO
anovelmous_grammar.egg-info/SOURCES.txt
anovelmous_grammar.egg-info/dependency_links.txt
anovelmous_grammar.egg-info/requires.txt
anovelmous_grammar.egg-info/top_level.txt
grammar/__init__.py