Metadata-Version: 1.0
Name: anovelmous-grammar
Version: 0.1.3
Summary: Grammar module for the anovelmous collaborative writing app.
Home-page: UNKNOWN
Author: Greg Ziegan
Author-email: greg.ziegan@gmail.com
License: MIT
Platform: UNKNOWN
